<?xml version="1.0" encoding="UTF-8"?><record_update table="sys_sg_ui_parameter">
    <sys_sg_ui_parameter action="DELETE">
        <button display_value="Edit Button - Usage Data for Applications - Application usage - List">7b7b0554c3f8311066fa241ce0013169</button>
        <button_parent_table>ua_app_usage</button_parent_table>
        <carried>false</carried>
        <constant/>
        <default_value/>
        <default_value_type>source_field</default_value_type>
        <field_name>app_type</field_name>
        <input_source>user</input_source>
        <input_style>inline</input_style>
        <input_type>list</input_type>
        <mandatory>false</mandatory>
        <max_entries/>
        <multi_entry>false</multi_entry>
        <multi_select>false</multi_select>
        <name>Application Type</name>
        <order/>
        <parameter_type>button</parameter_type>
        <placeholder/>
        <screen/>
        <search_type>starts_with</search_type>
        <source_field>app_type</source_field>
        <sys_class_name>sys_sg_ui_parameter</sys_class_name>
        <sys_created_by>admin</sys_created_by>
        <sys_created_on>2023-08-17 15:11:57</sys_created_on>
        <sys_id>b37b0554c3f8311066fa241ce0013182</sys_id>
        <sys_mod_count>0</sys_mod_count>
        <sys_name>Application Type</sys_name>
        <sys_package display_value="Case" source="x_1070541_case_0">434ac41ac320311066fa241ce00131bb</sys_package>
        <sys_policy/>
        <sys_scope display_value="Case">434ac41ac320311066fa241ce00131bb</sys_scope>
        <sys_update_name>sys_sg_ui_parameter_b37b0554c3f8311066fa241ce0013182</sys_update_name>
        <sys_updated_by>admin</sys_updated_by>
        <sys_updated_on>2023-08-17 15:11:57</sys_updated_on>
        <table_name>ua_app_usage</table_name>
        <virtual_field_value>false</virtual_field_value>
    </sys_sg_ui_parameter>
    <sys_translated_text action="DELETE" query="documentkey=b37b0554c3f8311066fa241ce0013182"/>
    <sys_update_version action="INSERT_OR_UPDATE">
        <action>DELETE</action>
        <application display_value="Case">434ac41ac320311066fa241ce00131bb</application>
        <file_path/>
        <instance_id>b3deb2d6dbcf4110f492c597059619c2</instance_id>
        <instance_name>dev126550</instance_name>
        <name>sys_sg_ui_parameter_b37b0554c3f8311066fa241ce0013182</name>
        <payload><![CDATA[<?xml version="1.0" encoding="UTF-8"?><record_update table="sys_sg_ui_parameter"><sys_sg_ui_parameter action="INSERT_OR_UPDATE"><button display_value="Edit Button - Usage Data for Applications - Application usage - List">7b7b0554c3f8311066fa241ce0013169</button><button_parent_table>ua_app_usage</button_parent_table><carried>false</carried><constant/><default_value/><default_value_type>source_field</default_value_type><field_name>app_type</field_name><input_source>user</input_source><input_style>inline</input_style><input_type>list</input_type><mandatory>false</mandatory><max_entries/><multi_entry>false</multi_entry><multi_select>false</multi_select><name>Application Type</name><order/><parameter_type>button</parameter_type><placeholder/><screen/><search_type>starts_with</search_type><source_field>app_type</source_field><sys_class_name>sys_sg_ui_parameter</sys_class_name><sys_created_by>admin</sys_created_by><sys_created_on>2023-08-17 15:11:57</sys_created_on><sys_id>b37b0554c3f8311066fa241ce0013182</sys_id><sys_mod_count>0</sys_mod_count><sys_name>Application Type</sys_name><sys_package display_value="Case" source="x_1070541_case_0">434ac41ac320311066fa241ce00131bb</sys_package><sys_policy/><sys_scope display_value="Case">434ac41ac320311066fa241ce00131bb</sys_scope><sys_update_name>sys_sg_ui_parameter_b37b0554c3f8311066fa241ce0013182</sys_update_name><sys_updated_by>admin</sys_updated_by><sys_updated_on>2023-08-17 15:11:57</sys_updated_on><table_name>ua_app_usage</table_name><virtual_field_value>false</virtual_field_value></sys_sg_ui_parameter><sys_translated_text action="delete_multiple" query="documentkey=b37b0554c3f8311066fa241ce0013182"/></record_update>]]></payload>
        <payload_hash>-1414394162</payload_hash>
        <record_name>Application Type</record_name>
        <reverted_from/>
        <source>b17e211ec3a4311066fa241ce0013164</source>
        <source_table>sys_update_set</source_table>
        <state>previous</state>
        <sys_created_by>admin</sys_created_by>
        <sys_created_on>2023-08-17 15:11:57</sys_created_on>
        <sys_id>377b0554c3f8311066fa241ce0013184</sys_id>
        <sys_mod_count>0</sys_mod_count>
        <sys_recorded_at>18a040da4d50000001</sys_recorded_at>
        <sys_updated_by>admin</sys_updated_by>
        <sys_updated_on>2023-08-17 15:11:57</sys_updated_on>
        <type>UI parameter</type>
        <update_guid>7f7b055487f831109e48a6572ba98283</update_guid>
        <update_guid_history>7f7b055487f831109e48a6572ba98283:-1414394162</update_guid_history>
    </sys_update_version>
    <sys_metadata_delete action="INSERT_OR_UPDATE">
        <sys_audit_delete/>
        <sys_class_name>sys_metadata_delete</sys_class_name>
        <sys_created_by>admin</sys_created_by>
        <sys_created_on>2023-08-17 15:29:48</sys_created_on>
        <sys_db_object display_value="" name="sys_sg_ui_parameter">sys_sg_ui_parameter</sys_db_object>
        <sys_id>09c4390c2791491fa3b5958b876d6a11</sys_id>
        <sys_metadata>b37b0554c3f8311066fa241ce0013182</sys_metadata>
        <sys_mod_count>0</sys_mod_count>
        <sys_name>Application Type</sys_name>
        <sys_package display_value="Case" source="x_1070541_case_0">434ac41ac320311066fa241ce00131bb</sys_package>
        <sys_parent/>
        <sys_policy/>
        <sys_scope display_value="Case">434ac41ac320311066fa241ce00131bb</sys_scope>
        <sys_scope_delete display_value="">0e2cee2ef4ec4e5c84df03602f067710</sys_scope_delete>
        <sys_update_name>sys_sg_ui_parameter_b37b0554c3f8311066fa241ce0013182</sys_update_name>
        <sys_update_version display_value="sys_sg_ui_parameter_b37b0554c3f8311066fa241ce0013182">377b0554c3f8311066fa241ce0013184</sys_update_version>
        <sys_updated_by>admin</sys_updated_by>
        <sys_updated_on>2023-08-17 15:29:48</sys_updated_on>
    </sys_metadata_delete>
</record_update>
